plover_phenrsteno.py
phenrsteno/__init__.py
plover_phenrsteno-0.2.3.dist-info/DESCRIPTION.rst
plover_phenrsteno-0.2.3.dist-info/METADATA
plover_phenrsteno-0.2.3.dist-info/RECORD
plover_phenrsteno-0.2.3.dist-info/WHEEL
plover_phenrsteno-0.2.3.dist-info/entry_points.txt
plover_phenrsteno-0.2.3.dist-info/metadata.json
plover_phenrsteno-0.2.3.dist-info/top_level.txt
plover_phenrsteno-0.2.3.dist-info/zip-safe
