Metadata-Version: 2.0
Name: plover-phenrsteno
Version: 0.2.3
Summary: Phonemic non-rhotic English stenotype system for Plover
Home-page: https://github.com/contrum/plover-phenrsteno
Author: Gregory Chamberlain
Author-email: 15685804+contrum@users.noreply.github.com
License: GNU General Public License v2 or later (GPLv2+)
Keywords: plover plover_plugin
Platform: UNKNOWN
Classifier: Programming Language :: Python :: 3
Classifier: License :: OSI Approved :: GNU General Public License v2 or later (GPLv2+)
Classifier: Operating System :: OS Independent
Classifier: Environment :: Plugins
Classifier: Intended Audience :: End Users/Desktop
Requires-Dist: plover (>=4.0.0.dev0)
